json2pystmt/__init__.py
json2pystmt/__main__.py
json2pystmt/json2pystmt.py
json2pystmt-0.4.0.dist-info/METADATA
json2pystmt-0.4.0.dist-info/WHEEL
json2pystmt-0.4.0.dist-info/entry_points.txt
json2pystmt-0.4.0.dist-info/licenses/LICENSE
json2pystmt-0.4.0.dist-info/RECORD
