Metadata-Version: 2.4
Name: json2pystmt
Version: 0.4.0
Summary: Convert JSON to Python assignment statements. Useful for grepping JSON, diffing JSON objects, and debugging.
Project-URL: Homepage, https://github.com/atsuoishimoto/json2pystmt
Project-URL: Repository, https://github.com/atsuoishimoto/json2pystmt
Project-URL: Issues, https://github.com/atsuoishimoto/json2pystmt/issues
Author-email: Atsuo Ishimoto <atsuoishimoto@gmail.com>
License-Expression: MIT
License-File: LICENSE
Requires-Python: >=3.10
